eggai_clutch/__init__.py
eggai_clutch/clutch.py
eggai_clutch/exceptions.py
eggai_clutch/message.py
eggai_clutch/strategy.py
eggai_clutch-0.2.0.dist-info/METADATA
eggai_clutch-0.2.0.dist-info/WHEEL
eggai_clutch-0.2.0.dist-info/licenses/LICENSE
eggai_clutch-0.2.0.dist-info/RECORD
