Metadata-Version: 2.4
Name: eggai-clutch
Version: 0.2.0
Summary: Multi-agent orchestration for EggAI
Project-URL: Homepage, https://github.com/eggai-tech/eggai-clutch
Project-URL: Repository, https://github.com/eggai-tech/eggai-clutch
Author-email: EggAI <info@eggai.tech>
License-Expression: MIT
License-File: LICENSE
Classifier: Development Status :: 3 - Alpha
Classifier: Intended Audience :: Developers
Classifier: License :: OSI Approved :: MIT License
Classifier: Programming Language :: Python :: 3
Classifier: Programming Language :: Python :: 3.10
Classifier: Programming Language :: Python :: 3.11
Classifier: Programming Language :: Python :: 3.12
Classifier: Programming Language :: Python :: 3.13
Requires-Python: >=3.10
Requires-Dist: eggai>=0.2.9
Requires-Dist: pydantic>=2.0
Provides-Extra: a2a
Requires-Dist: eggai[a2a]; extra == 'a2a'
Provides-Extra: cli
Requires-Dist: eggai[cli]; extra == 'cli'
Provides-Extra: dev
Requires-Dist: pytest; extra == 'dev'
Requires-Dist: pytest-asyncio; extra == 'dev'
Requires-Dist: pytest-cov; extra == 'dev'
Requires-Dist: ruff; extra == 'dev'
Provides-Extra: mcp
Requires-Dist: eggai[mcp]; extra == 'mcp'
